asymmetric/__init__.py
asymmetric/elliptic_curve.py
asymmetric/rsa.py
hash/__init__.py
hash/md5.py
hash/sha1.py
symmetric/__init__.py
symmetric/aes128.py
symmetric/des.py
mycryptool-1.1.1.dist-info/METADATA
mycryptool-1.1.1.dist-info/WHEEL
mycryptool-1.1.1.dist-info/top_level.txt
mycryptool-1.1.1.dist-info/RECORD
