Metadata-Version: 2.1
Name: mycryptool
Version: 1.1.1
Summary: A python package that include commonly used cryptographic algorithm and tools.
Home-page: https://github.com/ChopperCP/MyCrptool
Author: ChopperCP
Author-email: 568624486@qq.com
License: UNKNOWN
Platform: UNKNOWN
Classifier: Programming Language :: Python :: 3
Classifier: License :: OSI Approved :: MIT License
Classifier: Operating System :: OS Independent
